vmCall/__init__.py
vmCall/vmCall.py
vmCall-0.0.0.3.dist-info/METADATA
vmCall-0.0.0.3.dist-info/WHEEL
vmCall-0.0.0.3.dist-info/top_level.txt
vmCall-0.0.0.3.dist-info/RECORD
